rfpOperationsTest3/__init__.py
rfpOperationsTest3/database/__init__.py
rfpOperationsTest3/database/create.py
rfpOperationsTest3/database/delete.py
rfpOperationsTest3/database/funcs.py
rfpOperationsTest3/database/instance.py
rfpOperationsTest3/database/update.py
rfpOperationsTest3/identifier/__init__.py
rfpOperationsTest3/identifier/event.py
rfpOperationsTest3/identifier/hash_p_feature.py
rfpOperationsTest3/identifier/prop_identifier.py
rfpOperationsTest3/scraper/__init__.py
rfpOperationsTest3/scraper/base.py
rfpOperationsTest3/scraper/zoopla.py
rfpOperationsTest3-0.0.1.dist-info/METADATA
rfpOperationsTest3-0.0.1.dist-info/WHEEL
rfpOperationsTest3-0.0.1.dist-info/top_level.txt
rfpOperationsTest3-0.0.1.dist-info/RECORD
