Metadata-Version: 2.1
Name: rfpOperationsTest3
Version: 0.0.1
Summary: This package includes some functions for rental-flat-project
Home-page: UNKNOWN
Author: Borhan
Author-email: <han.kagan.b@gmail.com>
License: UNKNOWN
Keywords: python,rfp package
Platform: UNKNOWN
Classifier: Development Status :: 3 - Alpha
Classifier: Intended Audience :: Education
Classifier: Programming Language :: Python :: 2
Classifier: Programming Language :: Python :: 3
Classifier: Operating System :: MacOS :: MacOS X
Classifier: Operating System :: Microsoft :: Windows
